{"cameraMode":{"drawMode":0,"name":"Shaded","section":"Shading Mode"},"sceneLighting":true,"audioPlay":false,"sceneViewState":{"m_AlwaysRefresh":false,"showFog":true,"showSkybox":true,"showFlares":true,"showImageEffects":true,"showParticleSystems":true,"showVisualEffectGraphs":true,"m_FxEnabled":true},"in2DMode":false,"pivot":{"x":-4.847015380859375,"y":1.9464459419250489,"z":2.1855950355529787},"rotation":{"x":0.04342863708734512,"y":0.468379408121109,"z":0.023058529943227769,"w":-0.8821588158607483},"size":5.557884693145752,"orthographic":false}